{
  "999": {
    "zh": "999（英国紧急电话）",
    "note": "UK emergency number for police, fire, or ambulance"
  },
  "flat white": {
    "zh": "澄白咖啡",
    "note": "A popular UK coffee order — espresso with steamed milk, similar to a latte but stronger and smaller."
  },
  "take away": {
    "zh": "外带",
    "note": "British English for 'to go' (American English). E.g. 'a takeaway coffee', 'shall we get a takeaway tonight?'"
  },
  "oat milk": {
    "zh": "燕麦奶",
    "note": "A common dairy-free milk alternative, widely available in UK cafés."
  },
  "grand": {
    "zh": "太好了 / 很棒",
    "note": "Informal British way of saying 'great' or 'that's fine'. Common in everyday chat, not about money here."
  },
  "excuse me": {
    "zh": "打扰一下",
    "note": "Polite way to get someone's attention before asking a question."
  },
  "station": {
    "zh": "车站",
    "note": "Can mean train station or tube (underground) station depending on context."
  },
  "round the corner": {
    "zh": "在拐角处 / 附近",
    "note": "Means very close by. 'Round' is the British spelling/usage of 'around'."
  },
  "you can't miss it": {
    "zh": "你一定能找到",
    "note": "A common phrase when giving directions, meaning it's obvious/easy to spot."
  },
  "hiya": {
    "zh": "嗨",
    "note": "A casual, friendly version of 'hi', very common among students and young people in the UK."
  },
  "flatmate": {
    "zh": "室友",
    "note": "British English for someone you share a flat/apartment with (American English: roommate)."
  },
  "a bit of a state": {
    "zh": "有点乱 / 一团糟",
    "note": "Informal way of saying something is messy or in poor condition."
  },
  "sizes": {
    "zh": "尺寸/杯型",
    "note": "Drink size options"
  },
  "medium": {
    "zh": "中杯/中号",
    "note": "UK cafés: small/medium/large or regular/large"
  },
  "decaf": {
    "zh": "低咖啡因的",
    "note": "Short for \"decaffeinated\""
  },
  "what can i get for you": {
    "zh": "需要点什么",
    "note": "Friendly way to ask for an order"
  },
  "extra shot": {
    "zh": "加一份浓缩",
    "note": "Adds one shot of espresso"
  },
  "no sugar": {
    "zh": "不加糖",
    "note": "Common way to decline sugar"
  },
  "almond milk": {
    "zh": "杏仁奶",
    "note": "Dairy-free milk alternative"
  },
  "allergic": {
    "zh": "过敏的",
    "note": "Used for food allergies"
  },
  "grab": {
    "zh": "Casual for \"get/take\"",
    "note": "顺便拿/要"
  },
  "for here": {
    "zh": "在这里用",
    "note": "Eating/drinking in the café"
  },
  "to go": {
    "zh": "带走",
    "note": "UK also says \"takeaway\""
  },
  "cash only": {
    "zh": "只收现金",
    "note": "No card payment accepted"
  },
  "contactless": {
    "zh": "非接触支付",
    "note": "Tap-to-pay by card or phone"
  },
  "altogether": {
    "zh": "总共",
    "note": "Total price"
  },
  "pop": {
    "zh": "放/摆",
    "note": "Casual \"put\" — very British"
  },
  "give us": {
    "zh": "给我们",
    "note": "Informal \"give me/us\" — common in service settings"
  },
  "wrong order": {
    "zh": "点错了",
    "note": "When the order doesn't match"
  },
  "sort out": {
    "zh": "处理好",
    "note": "To fix/resolve a problem"
  },
  "have a good one": {
    "zh": "祝你愉快",
    "note": "Casual farewell"
  },
  "next door": {
    "zh": "隔壁",
    "note": "The room/flat right beside yours"
  },
  "give us a shout": {
    "zh": "叫我一声",
    "note": "Informal 'give me/us' — very British, means 'let me know'"
  },
  "then": {
    "zh": "那么/呢",
    "note": "Conversational filler at the end of a question, softens it"
  },
  "on the side": {
    "zh": "在台面上",
    "note": "On the kitchen counter/worktop"
  },
  "hob": {
    "zh": "炉灶/灶台",
    "note": "British word for stovetop"
  },
  "cuppa": {
    "zh": "一杯茶",
    "note": "Casual short for 'a cup of tea'"
  },
  "stick": {
    "zh": "贴/放",
    "note": "Casual for 'put' or 'attach', e.g. 'stick a label on it'"
  },
  "washing up": {
    "zh": "洗碗",
    "note": "British term for washing dishes (not laundry)"
  },
  "rota": {
    "zh": "轮值表",
    "note": "A rota is a schedule/rotation list, e.g. for chores"
  },
  "your bit": {
    "zh": "你那一份",
    "note": "Your share of something, e.g. a shared bill"
  },
  "spare": {
    "zh": "备用的/多余的",
    "note": "An extra one you're not currently using"
  },
  "help yourself": {
    "zh": "请自便",
    "note": "Invites someone to take/use something freely"
  },
  "too loud": {
    "zh": "太吵",
    "note": "Excessive noise level"
  },
  "keep it down": {
    "zh": "小声点",
    "note": "Asking someone to reduce noise"
  },
  "mate": {
    "zh": "朋友/哥们",
    "note": "Very common British word for friend"
  },
  "the more the merrier": {
    "zh": "人越多越热闹",
    "note": "A set phrase welcoming more people to join"
  },
  "nabbed": {
    "zh": "抢到/占到",
    "note": "Casual past tense of 'nab', meaning grabbed quickly"
  },
  "proper": {
    "zh": "非常/特别",
    "note": "British informal intensifier, e.g. 'proper busy' = very busy"
  },
  "on the blink": {
    "zh": "坏掉了/不正常了",
    "note": "Informal way to say a device/appliance isn't working properly"
  },
  "pop a ticket in": {
    "zh": "提交一个报修单",
    "note": "Casual for submitting a maintenance request"
  },
  "sorry to bother you": {
    "zh": "不好意思打扰一下",
    "note": "Polite way to open a request to a stranger"
  },
  "carry on": {
    "zh": "继续/一直走",
    "note": "Keep going in the same direction"
  },
  "take the first left": {
    "zh": "第一个路口左转",
    "note": "Common direction-giving phrase"
  },
  "five-minute walk": {
    "zh": "五分钟的步行路程",
    "note": "Describes walking distance in time"
  },
  "postbox": {
    "zh": "邮筒",
    "note": "British term for a street mailbox, usually bright red"
  },
  "walking distance": {
    "zh": "步行可到的距离",
    "note": "Close enough to walk to"
  },
  "get into town": {
    "zh": "去市中心",
    "note": "'Town' often means the town/city centre in British English"
  },
  "hop on": {
    "zh": "上车",
    "note": "Casual way to say 'get on' a bus or train"
  },
  "not from round here": {
    "zh": "不是本地人",
    "note": "Explains unfamiliarity with the local area"
  },
  "walk you through": {
    "zh": "详细说明/一步步讲解",
    "note": "To explain something step by step"
  },
  "roundabout": {
    "zh": "环岛",
    "note": "Circular road junction, very common in the UK"
  },
  "tucked behind": {
    "zh": "藏/位于...后面",
    "note": "Describes something set back from the main view, slightly hidden"
  },
  "heading": {
    "zh": "朝...方向走",
    "note": "Moving in a particular direction"
  },
  "the wrong way": {
    "zh": "走错方向",
    "note": "Opposite of the correct direction"
  },
  "give it a go": {
    "zh": "试一试",
    "note": "Casual British phrase meaning 'try it'"
  },
  "shortcut": {
    "zh": "近路/捷径",
    "note": "A quicker route"
  },
  "cut through": {
    "zh": "穿过/抄近路",
    "note": "To pass through a place as a shortcut"
  },
  "a bit lost": {
    "zh": "有点迷路",
    "note": "Softened way of admitting you don't know where you are"
  },
  "no bother": {
    "zh": "没关系/不麻烦",
    "note": "Casual reassurance, similar to 'no problem'"
  },
  "ever so much": {
    "zh": "非常/十分",
    "note": "British intensifier often paired with 'thanks', e.g. 'thanks ever so much'"
  },
  "sore throat": {
    "zh": "喉咙痛",
    "note": "Common minor ailment asked about at a pharmacy"
  },
  "cold": {
    "zh": "感冒",
    "note": "Common illness, distinct from 'flu' which is more severe"
  },
  "as needed": {
    "zh": "按需",
    "note": "Take medicine only when the symptom occurs, not on a fixed schedule"
  },
  "empty stomach": {
    "zh": "空腹",
    "note": "Without having eaten; relevant for medicine instructions"
  },
  "book an appointment": {
    "zh": "预约",
    "note": "To schedule a time to see a doctor"
  },
  "what seems to be the problem": {
    "zh": "哪里不舒服",
    "note": "Standard doctor's opening question"
  },
  "a bit off": {
    "zh": "有点不舒服",
    "note": "Mild, informal way to describe feeling unwell"
  },
  "it hurts": {
    "zh": "疼",
    "note": "Used to describe pain when pointing to a spot"
  },
  "prescription": {
    "zh": "处方",
    "note": "A doctor's written authorisation for medicine"
  },
  "pick up": {
    "zh": "取（药）",
    "note": "To collect something, e.g. a prescription from the pharmacy"
  },
  "clear up": {
    "zh": "好转/痊愈",
    "note": "For symptoms or an illness to resolve"
  },
  "life-threatening": {
    "zh": "危及生命的",
    "note": "Describes a serious, urgent medical condition"
  },
  "on its way": {
    "zh": "正在赶来",
    "note": "Something (e.g. help) is currently travelling towards you"
  },
  "all of a sudden": {
    "zh": "突然",
    "note": "Describes something happening unexpectedly and quickly"
  },
  "stay calm": {
    "zh": "保持冷静",
    "note": "Common reassurance during a stressful or urgent situation"
  },
  "call in sick": {
    "zh": "请病假",
    "note": "To notify someone you won't attend due to illness"
  },
  "get well soon": {
    "zh": "早日康复",
    "note": "Common well-wish said to someone who is ill"
  },
  "a&e": {
    "zh": "急诊科",
    "note": "Accident & Emergency — the UK term for the ER"
  },
  "gp surgery": {
    "zh": "全科诊所",
    "note": "British term for a local doctor's practice/clinic"
  },
  "is this seat taken": {
    "zh": "这个座位有人坐吗",
    "note": "Polite way to check before sitting down in a lecture or seminar"
  },
  "didn't quite catch it": {
    "zh": "没太听清",
    "note": "Polite way to ask someone to repeat what they said"
  },
  "seminar": {
    "zh": "研讨课",
    "note": "Small-group discussion class, distinct from a lecture"
  },
  "stuck on": {
    "zh": "卡在（某个问题上）",
    "note": "Unable to progress past a particular point"
  },
  "office hours": {
    "zh": "答疑时间",
    "note": "Set times when a tutor/lecturer is available for questions"
  },
  "on the right track": {
    "zh": "方向正确",
    "note": "Making good progress in the right direction"
  },
  "deadline": {
    "zh": "截止日期",
    "note": "The date work must be submitted by"
  },
  "extension": {
    "zh": "延期",
    "note": "Extra time granted to submit work late"
  },
  "student portal": {
    "zh": "学生系统",
    "note": "The university's online system for grades, enrolment, etc."
  },
  "wifi": {
    "zh": "无线网络",
    "note": "Wireless internet, commonly needed across campus"
  },
  "print": {
    "zh": "打印",
    "note": "To produce a paper copy, often needed for essays/handouts"
  },
  "reserve": {
    "zh": "预约",
    "note": "To book something in advance, e.g. a study room"
  },
  "group project": {
    "zh": "小组作业",
    "note": "Coursework completed together with classmates"
  },
  "swap numbers": {
    "zh": "交换电话号码",
    "note": "Exchanging contact details, common when arranging group work"
  },
  "society": {
    "zh": "社团",
    "note": "A student club based around a shared interest"
  },
  "workload": {
    "zh": "工作量/作业量",
    "note": "The amount of academic work you have to do"
  },
  "back to back": {
    "zh": "连续不间断",
    "note": "One after another with no break in between"
  },
  "sign up": {
    "zh": "报名/注册",
    "note": "To register for something, e.g. a module or event"
  },
  "good luck": {
    "zh": "祝你好运/顺利",
    "note": "Common well-wish before an exam or challenge"
  },
  "freshers' fair": {
    "zh": "新生迎新集市",
    "note": "An event at the start of term where new students explore clubs/societies"
  },
  "bit chilly": {
    "zh": "有点冷",
    "note": "Mild, understated way to say it's cold"
  },
  "typical british weather": {
    "zh": "典型的英国天气",
    "note": "Common jokey remark about how quickly UK weather changes"
  },
  "make the most of": {
    "zh": "充分利用/好好享受",
    "note": "To take full advantage of something while you can"
  },
  "alright": {
    "zh": "你好/还好吗",
    "note": "Very common casual British greeting, often said as a question"
  },
  "long time no see": {
    "zh": "好久不见",
    "note": "Said when meeting someone you haven't seen in a while"
  },
  "can't complain": {
    "zh": "还不错/没什么好抱怨的",
    "note": "Casual, modest way of saying things are fine"
  },
  "treating you": {
    "zh": "对你怎么样",
    "note": "Used in 'how's X treating you', asking how an experience has been"
  },
  "fancy": {
    "zh": "想不想/要不要",
    "note": "Casual way to suggest or ask if someone wants something"
  },
  "up to": {
    "zh": "在做什么/有什么安排",
    "note": "Used in 'what are you up to', asking about someone's plans/activities"
  },
  "free": {
    "zh": "有空",
    "note": "Available, not busy"
  },
  "pencil in": {
    "zh": "先定一个大概时间",
    "note": "To tentatively schedule something, open to change later"
  },
  "well up for": {
    "zh": "很想去/很乐意",
    "note": "Casual enthusiastic way of agreeing to something"
  },
  "sounds good": {
    "zh": "听起来不错",
    "note": "Casual way to agree to a plan"
  },
  "can't make it": {
    "zh": "去不了",
    "note": "Polite way to decline an invitation due to unavailability"
  },
  "another time": {
    "zh": "下次吧",
    "note": "Suggests rescheduling for later"
  },
  "rain check": {
    "zh": "改天再约",
    "note": "Idiom for postponing an invitation to a later date"
  },
  "what are you having": {
    "zh": "你想喝点什么",
    "note": "Common phrase when offering to buy someone a drink"
  },
  "my round": {
    "zh": "这轮我请",
    "note": "Pub custom: taking a turn to buy drinks for the group"
  },
  "cheers": {
    "zh": "干杯/谢谢",
    "note": "Used both as a toast and as a casual thank-you"
  },
  "same again": {
    "zh": "再来一样的",
    "note": "Ordering another of the same drink"
  },
  "nice one": {
    "zh": "干得漂亮/真棒",
    "note": "Casual praise or approval"
  },
  "having a laugh": {
    "zh": "开玩笑",
    "note": "Used in 'you're having a laugh', meaning 'you must be joking'"
  },
  "give over": {
    "zh": "别闹了/得了吧",
    "note": "Informal British way of telling someone to stop, often in jest"
  },
  "well into": {
    "zh": "很喜欢/很投入",
    "note": "Enthusiastic about a hobby or interest at the moment"
  },
  "spare time": {
    "zh": "空闲时间",
    "note": "Free time outside of work/study"
  },
  "brilliant": {
    "zh": "太棒了",
    "note": "Very common British word for excellent/great"
  },
  "rubbish": {
    "zh": "糟糕/差劲",
    "note": "Informal British word for something bad or of poor quality"
  },
  "fair enough": {
    "zh": "有道理/行吧",
    "note": "Casual acceptance of a reason or explanation, even if not fully agreeing"
  },
  "be a pain": {
    "zh": "添麻烦",
    "note": "Used in 'I don't want to be a pain', softening a request"
  },
  "no bother at all": {
    "zh": "一点都不麻烦",
    "note": "Reassurance that a request or favour is not a problem"
  },
  "a bit much": {
    "zh": "有点过分",
    "note": "Understated way of saying something is excessive"
  },
  "taking forever": {
    "zh": "花了好久",
    "note": "Informal complaint about something being slow"
  },
  "in the queue": {
    "zh": "在排队",
    "note": "'Queue' is the British word for a line of waiting people"
  },
  "this is": {
    "zh": "这是",
    "note": "Standard phrase for introducing someone"
  },
  "heard a lot about you": {
    "zh": "久仰大名",
    "note": "Polite phrase said when meeting someone you've heard about before"
  },
  "best be off": {
    "zh": "该走了",
    "note": "Casual British way of saying it's time to leave"
  },
  "catch you later": {
    "zh": "回头见",
    "note": "Casual farewell"
  },
  "take care": {
    "zh": "保重",
    "note": "Warm, common way to say goodbye"
  },
  "just browsing": {
    "zh": "随便看看",
    "note": "Common reply when a shop assistant offers help, meaning you don't need assistance yet"
  },
  "try on": {
    "zh": "试穿",
    "note": "To put on clothing to check fit before buying"
  },
  "fitting rooms": {
    "zh": "试衣间",
    "note": "British term for changing rooms in a clothes shop"
  },
  "size": {
    "zh": "尺码",
    "note": "UK clothing sizes differ from US/EU, worth double-checking"
  },
  "another colour": {
    "zh": "其他颜色",
    "note": "Asking if an item comes in a different colour option"
  },
  "too tight": {
    "zh": "太紧",
    "note": "Describes clothing that doesn't fit comfortably"
  },
  "in the sale": {
    "zh": "打折商品",
    "note": "British phrase for something reduced in price ('the sale' = discount period)"
  },
  "discount": {
    "zh": "折扣",
    "note": "A price reduction"
  },
  "% off": {
    "zh": "打折/减免百分比",
    "note": "Used to state a percentage discount, e.g. '20% off'"
  },
  "apple pay": {
    "zh": "Apple Pay",
    "note": "Mobile contactless payment method, widely accepted in the UK"
  },
  "pay by card": {
    "zh": "刷卡支付",
    "note": "Paying with a debit or credit card rather than cash"
  },
  "declined": {
    "zh": "被拒绝",
    "note": "When a card payment fails to go through"
  },
  "pin": {
    "zh": "密码",
    "note": "Personal Identification Number used to authorise card payments"
  },
  "return": {
    "zh": "退货",
    "note": "Bringing an item back to the shop, usually for a refund or exchange"
  },
  "receipt": {
    "zh": "收据",
    "note": "Proof of purchase, often required for returns"
  },
  "refund": {
    "zh": "退款",
    "note": "Getting your money back for a returned item"
  },
  "tag": {
    "zh": "标签",
    "note": "The label attached to new clothing, often needed intact for returns"
  },
  "bag": {
    "zh": "袋子",
    "note": "In UK supermarkets you're often asked if you need one, sometimes at a small charge"
  },
  "loyalty card": {
    "zh": "会员卡",
    "note": "A card used to collect points/discounts at a specific shop"
  },
  "self-checkout": {
    "zh": "自助结账",
    "note": "Machines that let customers scan and pay without a cashier"
  },
  "unexpected item": {
    "zh": "意外物品",
    "note": "Famous self-checkout error message ('unexpected item in the bagging area')"
  },
  "open a bank account": {
    "zh": "开银行账户",
    "note": "Common early task for international students settling in the UK"
  },
  "bank statement": {
    "zh": "银行对账单",
    "note": "A document showing account transactions over a period"
  },
  "balance": {
    "zh": "余额",
    "note": "The amount of money currently in an account"
  },
  "skint": {
    "zh": "手头紧/没钱",
    "note": "Very common British informal word for having little money"
  },
  "bargain": {
    "zh": "划算的交易",
    "note": "Something bought for a good, low price"
  }
}
